data_utils/__init__.py
data_utils/cli.py
data_utils11-0.1.0.dist-info/METADATA
data_utils11-0.1.0.dist-info/WHEEL
data_utils11-0.1.0.dist-info/entry_points.txt
data_utils11-0.1.0.dist-info/RECORD
