Metadata-Version: 2.4
Name: data-utils11
Version: 0.1.0
Summary: Simple data utilities package
Author: DaVita AI
Requires-Python: >=3.11
Requires-Dist: ml-core
Requires-Dist: polars
Requires-Dist: rich
Requires-Dist: typer
